curl/__init__.py
curl/core/__init__.py
curl/core/curllib.py
curl/core/requestslib.py
curl/main.py
curl_python-0.1.0.dist-info/LICENSE
curl_python-0.1.0.dist-info/METADATA
curl_python-0.1.0.dist-info/WHEEL
curl_python-0.1.0.dist-info/entry_points.txt
curl_python-0.1.0.dist-info/RECORD
