Metadata-Version: 2.1
Name: curl-python
Version: 0.1.0
Summary: 
Author: hermann-web
Author-email: hermannagossou6@gmail.com
Requires-Python: >=3.6,<4.0
Classifier: Programming Language :: Python :: 3
Classifier: Programming Language :: Python :: 3.6
Classifier: Programming Language :: Python :: 3.7
Classifier: Programming Language :: Python :: 3.8
Classifier: Programming Language :: Python :: 3.9
Classifier: Programming Language :: Python :: 3.10
Classifier: Programming Language :: Python :: 3.11
Classifier: Programming Language :: Python :: 3.12
Requires-Dist: requests (>=2.20.0,<3.0.0)
Requires-Dist: tqdm (>=4.60.2,<5.0.0)
